[
    {
      "id": "pr",
      "legend": "Partido Republicano",
      "name": "Partido Republicano",
      "seats": 3
    },
    {
        "id": "chv",
        "legend": "Chile Vamos",
        "name": "Chile Vamos",
        "seats": 71
    },
    {
        "id": "oder",
        "legend": "Otros Derecha",
        "name": "Otros Derecha",
        "seats": 2
    },
    {
        "id": "dc",
        "legend": "DC+CIU",
        "name": "Democracia Cristiana",
        "seats": 20
    },
    {
        "id": "nm",
        "legend": "Nueva Mayoría",
        "name": "Nueva Mayoría",
        "seats": 39
    },
    {
        "id": "fa",
        "legend": "Frente Amplio",
        "name": "Frente Amplio",
        "seats": 14
    },
    {
        "id": "izq",
        "legend": "PC+PRO+PH+PI",
        "name": "Izquierda",
        "seats": 24
    }
]
